
{
    "File":{
        "Date":"2022/12/01 11:27:32",
        "Activity":"MIS",
        "Type":4
    },
    "Parameter_8":{
        "Number":"8",
        "Length":"8",
        "Status":"Good",
        "Time":"2022:335:17:11:52.812",
        "Type":"2",
        "Value":"142.068"
    },
    "Parameter_9":{
        "Number":"9",
        "Length":"8",
        "Status":"Good",
        "Time":"2022:335:17:11:52.812",
        "Type":"2",
        "Value":"136.11"
    },
    "Parameter_10":{
        "Number":"10",
        "Length":"8",
        "Status":"Good",
        "Time":"2022:335:17:11:52.812",
        "Type":"2",
        "Value":"129.507"
    },
    "Parameter_11":{
        "Number":"11",
        "Length":"8",
        "Status":"Good",
        "Time":"2022:335:17:11:52.812",
        "Type":"2",
        "Value":"131.194"
    },
    "Parameter_14":{
        "Number":"14",
        "Length":"2",
        "Status":"Good",
        "Time":"2022:335:17:11:52.812",
        "Type":"12",
        "Value":"PM"
    },
    "Parameter_21":{
        "Number":"21",
        "Length":"8",
        "Status":"Good",
        "Time":"2022:335:17:11:52.812",
        "Type":"2",
        "Value":"14.1791"
    },
    "Parameter_22":{
        "Number":"22",
        "Length":"0",
        "Status":"Good",
        "Time":"2022:335:17:11:52.812",
        "Type":"12",
        "Value":""
    },
    "Parameter_23":{
        "Number":"23",
        "Length":"8",
        "Status":"Good",
        "Time":"2022:335:17:11:52.812",
        "Type":"2",
        "Value":"2.4"
    },
    "Parameter_27":{
        "Number":"27",
        "Length":"8",
        "Status":"Good",
        "Time":"2022:335:17:11:52.812",
        "Type":"2",
        "Value":"23218.9"
    }
}